cappi/__init__.py
cappi/clients.py
cappi-0.2.0.dist-info/METADATA
cappi-0.2.0.dist-info/WHEEL
cappi-0.2.0.dist-info/RECORD
